data_genie-1.4.1.dist-info/licenses/LICENSE
genie_pkg/__init__.py
genie_pkg/australia.py
genie_pkg/delimited_genie.py
genie_pkg/dqc.py
genie_pkg/fw_genie.py
genie_pkg/generators.py
genie_pkg/json_genie.py
genie_pkg/validators.py
genie_pkg/data/dqc_grammar.lark
genie_pkg/data/oz_postcodes.json
genie_pkg/data/wonderland.txt
data_genie-1.4.1.dist-info/METADATA
data_genie-1.4.1.dist-info/WHEEL
data_genie-1.4.1.dist-info/top_level.txt
data_genie-1.4.1.dist-info/RECORD
