Metadata-Version: 2.4
Name: data-genie
Version: 1.4.1
Summary: A small genie to generate test data
Home-page: https://github.com/mkeshav/data-genie.git
Author: Keshav Murthy
Author-email: mkeshav@gmail.com
Classifier: Programming Language :: Python :: 3
Classifier: License :: OSI Approved :: MIT License
Classifier: Operating System :: OS Independent
License-File: LICENSE
Requires-Dist: numpy<2
Requires-Dist: pandas==2.2.2
Requires-Dist: jinja2==3.1.3
Requires-Dist: markovify==0.9.0
Requires-Dist: lark-parser==0.11.3
Requires-Dist: data-science-types==0.2.23
Dynamic: author
Dynamic: author-email
Dynamic: classifier
Dynamic: description
Dynamic: description-content-type
Dynamic: home-page
Dynamic: license-file
Dynamic: requires-dist
Dynamic: summary
